mcp_database_server/__init__.py
mcp_database_server/config.py
mcp_database_server/database.py
mcp_database_server/server.py
mcp_database_server/types.py
mcp_database_server-0.1.4.dist-info/METADATA
mcp_database_server-0.1.4.dist-info/WHEEL
mcp_database_server-0.1.4.dist-info/entry_points.txt
mcp_database_server-0.1.4.dist-info/RECORD
