Metadata-Version: 2.4
Name: mcp-database-server
Version: 0.1.4
Summary: Add your description here
Author-email: OuZhencong <ozhencong@gmail.com>
Requires-Python: >=3.11
Requires-Dist: httpx>=0.28.1
Requires-Dist: mcp[cli]>=1.2.1
Requires-Dist: psycopg2-binary>=2.9.10
Requires-Dist: requests>=2.32.3
Requires-Dist: slugify>=0.0.1
Requires-Dist: sqlalchemy>=2.0.38
